pytest_fzf/__init__.py
pytest_fzf/main.py
pytest_fzf/previewer.py
pytest_fzf/py.typed
pytest_fzf-0.1.2.post1.dist-info/LICENSE
pytest_fzf-0.1.2.post1.dist-info/METADATA
pytest_fzf-0.1.2.post1.dist-info/WHEEL
pytest_fzf-0.1.2.post1.dist-info/entry_points.txt
pytest_fzf-0.1.2.post1.dist-info/top_level.txt
pytest_fzf-0.1.2.post1.dist-info/RECORD
