Metadata-Version: 2.1
Name: pytest-fzf
Version: 0.1.2.post1
Summary: fzf-based test selector for pytest
Author-email: Daniele Trifirò <dtrifiro@redhat.com>
License: GNU GPL v3.0
Project-URL: Issues, https://github.com/dtrifiro/pytest-fzf/issues
Project-URL: Source, https://github.com/dtrifiro/pytest-fzf
Classifier: Programming Language :: Python :: 3
Classifier: Programming Language :: Python :: 3.10
Classifier: Programming Language :: Python :: 3.11
Classifier: Programming Language :: Python :: 3.12
Classifier: Programming Language :: Python :: 3.13
Classifier: Development Status :: 4 - Beta
Requires-Python: >=3.8
License-File: LICENSE
Requires-Dist: iterfzf==1.4.0.54.3
Requires-Dist: pytest>=6.0.0
Requires-Dist: pygments>=2.15.0
Provides-Extra: tests
Requires-Dist: pytest-sugar==1.0.0; extra == "tests"
Requires-Dist: pytest-cov==5.0.0; extra == "tests"
Requires-Dist: pytest-mock==3.14.0; extra == "tests"
Requires-Dist: mypy==1.13.0; extra == "tests"
Requires-Dist: types-pygments>=2.15.0; extra == "tests"
Provides-Extra: dev
Requires-Dist: pytest-fzf[tests]; extra == "dev"
